astroqtpy/__init__.py
astroqtpy/basetree.py
astroqtpy/quadnode.py
astroqtpy/quadpoint.py
astroqtpy/quadtree.py
tests/__init__.py
tests/test_quadnode.py
tests/test_quadpoint.py
astroQTpy-0.2.0.dist-info/LICENSE
astroQTpy-0.2.0.dist-info/METADATA
astroQTpy-0.2.0.dist-info/WHEEL
astroQTpy-0.2.0.dist-info/top_level.txt
astroQTpy-0.2.0.dist-info/RECORD
