Metadata-Version: 2.1
Name: astroQTpy
Version: 0.2.0
Summary: astroQTpy implements a quadtree data structure to explore 2D parameter space
Home-page: https://github.com/CalebHarada/astroQTpy
Author: Caleb K. Harada
Author-email: charad@berkeley.edu
License: MIT
Keywords: Quadtree Astronomy
License-File: LICENSE
Requires-Dist: astropy
Requires-Dist: astroquery
Requires-Dist: matplotlib
Requires-Dist: numpy
Requires-Dist: pytest
Requires-Dist: rebound
Requires-Dist: sphinx
